odoo8_addon_logistic_requisition_donation-8.0.0.1.0-py2.7-nspkg.pth
odoo8_addon_logistic_requisition_donation-8.0.0.1.0.dist-info/top_level.txt
odoo8_addon_logistic_requisition_donation-8.0.0.1.0.dist-info/WHEEL
odoo8_addon_logistic_requisition_donation-8.0.0.1.0.dist-info/RECORD
odoo8_addon_logistic_requisition_donation-8.0.0.1.0.dist-info/metadata.json
odoo8_addon_logistic_requisition_donation-8.0.0.1.0.dist-info/DESCRIPTION.rst
odoo8_addon_logistic_requisition_donation-8.0.0.1.0.dist-info/METADATA
odoo8_addon_logistic_requisition_donation-8.0.0.1.0.dist-info/namespace_packages.txt
odoo_addons/logistic_requisition_donation/__openerp__.py
odoo_addons/logistic_requisition_donation/__init__.py
odoo_addons/logistic_requisition_donation/README.rst
odoo_addons/logistic_requisition_donation/security/groups.xml
odoo_addons/logistic_requisition_donation/i18n/logistic_requisition_donation.pot
odoo_addons/logistic_requisition_donation/i18n/fr.po
odoo_addons/logistic_requisition_donation/model/logistic_requisition.py
odoo_addons/logistic_requisition_donation/model/logistic_requisition_line.py
odoo_addons/logistic_requisition_donation/model/logistic_requisition_source.py
odoo_addons/logistic_requisition_donation/model/__init__.py
odoo_addons/logistic_requisition_donation/wizard/cost_estimate.py
odoo_addons/logistic_requisition_donation/wizard/__init__.py
odoo_addons/logistic_requisition_donation/tests/__init__.py
odoo_addons/logistic_requisition_donation/tests/test_auto_create_sources.py
